python_exchange_rates/__init__.py
python_exchange_rates/python_exchange_rates.py
abstract_python_exchange_rates-1.0.1.dist-info/LICENSE
abstract_python_exchange_rates-1.0.1.dist-info/METADATA
abstract_python_exchange_rates-1.0.1.dist-info/WHEEL
abstract_python_exchange_rates-1.0.1.dist-info/top_level.txt
abstract_python_exchange_rates-1.0.1.dist-info/RECORD
