Metadata-Version: 2.1
Name: abstract-python-exchange-rates
Version: 1.0.1
Summary: AbstractExchangeRates - Wrapper to quickly start using the powerful AbstractAPI's exchange rates service in your projects.
Home-page: https://github.com/abstractapi/python-exchange-rates
Author: Benjamin Bouchet
Author-email: libraries@abstractapi.com
License: UNKNOWN
Platform: UNKNOWN
Classifier: Programming Language :: Python :: 3.6
Classifier: Intended Audience :: Developers
Classifier: License :: OSI Approved :: MIT License
Requires-Dist: certifi (==2020.12.5)
Requires-Dist: chardet (==4.0.0)
Requires-Dist: idna (==2.10)
Requires-Dist: plotly (==4.14.3)
Requires-Dist: requests (==2.25.1)
Requires-Dist: urllib3 (==1.26.4)
Requires-Dist: wincertstore (==0.2)
Requires-Dist: python-dotenv (==0.17.0)
Requires-Dist: abstract-python-core (==1.1.0)
